[
    [
        "div",
        {
            "id":"track{id}}"
        },
        [
            [
                "div",
                {"class":"infos"},
                [
                    [
                        "span",
                        {"class":"author"},
                        "{name}"
                    ],
                    [
                        "span",
                        {"class":"date"},
                        "{date}"
                    ]
                ]
            ],
            [
                "div",
                {"class":"track"},
                "{txt}"
            ]
        ]
    ]
]